TRITON_SWMM_benchmarking/TRITON_SWMM_benchmarking.py
TRITON_SWMM_benchmarking/__init__.py
TRITON_SWMM_benchmarking/__main__.py
TRITON_SWMM_benchmarking/cli.py
TRITON_SWMM_benchmarking/utils.py
triton_swmm_benchmarking-0.1.0.dist-info/licenses/LICENSE
triton_swmm_benchmarking-0.1.0.dist-info/METADATA
triton_swmm_benchmarking-0.1.0.dist-info/WHEEL
triton_swmm_benchmarking-0.1.0.dist-info/entry_points.txt
triton_swmm_benchmarking-0.1.0.dist-info/top_level.txt
triton_swmm_benchmarking-0.1.0.dist-info/RECORD
